blast_aligner/BlastResults.py
blast_aligner/BlastRow.py
blast_aligner/SeqInterval.py
blast_aligner/__init__.py
blast_aligner/commandline.py
BlastAlignmentJoiner-0.2.3.dist-info/LICENSE
BlastAlignmentJoiner-0.2.3.dist-info/METADATA
BlastAlignmentJoiner-0.2.3.dist-info/WHEEL
BlastAlignmentJoiner-0.2.3.dist-info/entry_points.txt
BlastAlignmentJoiner-0.2.3.dist-info/top_level.txt
BlastAlignmentJoiner-0.2.3.dist-info/RECORD
